flarevel/__init__.py
flarevel/cli.py
flarevel/commands/__init__.py
flarevel/commands/make.py
flarevel-6.8.dist-info/LICENSE
flarevel-6.8.dist-info/METADATA
flarevel-6.8.dist-info/WHEEL
flarevel-6.8.dist-info/entry_points.txt
flarevel-6.8.dist-info/top_level.txt
flarevel-6.8.dist-info/RECORD
