Metadata-Version: 2.1
Name: flarevel
Version: 6.8
Summary: Flarevel is a command-line interface (CLI) tool that quickly scaffolds Flask projects with a robust Model-View-Controller (MVC) architecture. It generates a well-organized project structure, including dedicated folders for models, views, controllers, and configurations, enabling developers to start building scalable and maintainable Flask applications in no time. Flarevel streamlines the setup process, saving you time and ensuring a clean, modular foundation for your projects.
Home-page: https://github.com/Yorts11/flarevel
Author: Yorts
Author-email: casterr@protonmail.com
Classifier: Programming Language :: Python :: 3
Classifier: License :: OSI Approved :: MIT License
Classifier: Operating System :: OS Independent
Requires-Python: >=3.7
License-File: LICENSE
Requires-Dist: Click
